whoa.py
whoa-0.1.dist-info/LICENSE
whoa-0.1.dist-info/WHEEL
whoa-0.1.dist-info/METADATA
whoa-0.1.dist-info/RECORD
